LICENSE
MANIFEST.in
README.md
VERSION.txt
pyproject.toml
requirements.txt
requirements_dev.txt
requirements_test.txt
setup.cfg
setup.py
pytest_django_queries/__init__.py
pytest_django_queries/cli.py
pytest_django_queries/diff.py
pytest_django_queries/entry.py
pytest_django_queries/filters.py
pytest_django_queries/plugin.py
pytest_django_queries/tables.py
pytest_django_queries/utils.py
pytest_django_queries.egg-info/PKG-INFO
pytest_django_queries.egg-info/SOURCES.txt
pytest_django_queries.egg-info/dependency_links.txt
pytest_django_queries.egg-info/entry_points.txt
pytest_django_queries.egg-info/not-zip-safe
pytest_django_queries.egg-info/requires.txt
pytest_django_queries.egg-info/top_level.txt
pytest_django_queries/templates/default_bootstrap.jinja2